s3_provider/manifest.toml
s3_provider/s3_provider.py
s3_provider/test_s3_provider.py
opsbox_s3_provider-0.1.6.dist-info/LICENCE.txt
opsbox_s3_provider-0.1.6.dist-info/METADATA
opsbox_s3_provider-0.1.6.dist-info/WHEEL
opsbox_s3_provider-0.1.6.dist-info/entry_points.txt
opsbox_s3_provider-0.1.6.dist-info/top_level.txt
opsbox_s3_provider-0.1.6.dist-info/RECORD
